notificationforwarder/baseclass.py
notificationforwarder/email/formatter.py
notificationforwarder/email/forwarder.py
notificationforwarder/example/formatter.py
notificationforwarder/example/forwarder.py
notificationforwarder/json/__init__.py
notificationforwarder/json/logger.py
notificationforwarder/naemonlog/reporter.py
notificationforwarder/rabbitmq/formatter.py
notificationforwarder/rabbitmq/forwarder.py
notificationforwarder/syslog/formatter.py
notificationforwarder/syslog/forwarder.py
notificationforwarder/telegram/forwarder.py
notificationforwarder/text/__init__.py
notificationforwarder/text/logger.py
notificationforwarder/webhook/forwarder.py
notificationforwarder/bin_folder/notificationforwarder
omdnotificationforwarder-4.0.dist-info/METADATA
omdnotificationforwarder-4.0.dist-info/WHEEL
omdnotificationforwarder-4.0.dist-info/RECORD
